patinput/__init__.py
patinput/getch.py
patinput/input_pattern.py
patinput/patinput.py
patinput-0.1.0.dist-info/LICENSE
patinput-0.1.0.dist-info/METADATA
patinput-0.1.0.dist-info/WHEEL
patinput-0.1.0.dist-info/top_level.txt
patinput-0.1.0.dist-info/RECORD
