Metadata-Version: 2.1
Name: patinput
Version: 0.1.0
Summary: UNKNOWN
Home-page: https://github.com/amiraslanaslani/patinput
Author: Amir Aslan Aslani
License: UNKNOWN
Project-URL: Bug Tracker, https://github.com/amiraslanaslani/patinput/issues
Platform: UNKNOWN
Classifier: Programming Language :: Python
Classifier: Topic :: Software Development :: Libraries :: Python Modules
Classifier: License :: OSI Approved :: GNU Library or Lesser General Public License (LGPL)
Classifier: Operating System :: Microsoft :: Windows
Classifier: Operating System :: POSIX
Classifier: Operating System :: POSIX :: Linux
Classifier: Operating System :: Unix
Classifier: Environment :: Console
Requires-Python: >=3.6
License-File: LICENSE
